token_audit/__init__.py
token_audit/aggregation.py
token_audit/base_tracker.py
token_audit/bucket_config.py
token_audit/buckets.py
token_audit/claude_code_adapter.py
token_audit/cli.py
token_audit/codex_cli_adapter.py
token_audit/gemini_cli_adapter.py
token_audit/normalization.py
token_audit/pinned_config.py
token_audit/preferences.py
token_audit/pricing_api.py
token_audit/pricing_config.py
token_audit/privacy.py
token_audit/py.typed
token_audit/recommendations.py
token_audit/schema_analyzer.py
token_audit/session_manager.py
token_audit/smell_aggregator.py
token_audit/smells.py
token_audit/storage.py
token_audit/tasks.py
token_audit/token_estimator.py
token_audit/zombie_detector.py
token_audit/config_analyzer/__init__.py
token_audit/config_analyzer/analyzer.py
token_audit/config_analyzer/credential_detector.py
token_audit/config_analyzer/discovery.py
token_audit/config_analyzer/parsers.py
token_audit/config_analyzer/pinned_servers.py
token_audit/display/__init__.py
token_audit/display/ascii_mode.py
token_audit/display/base.py
token_audit/display/keyboard.py
token_audit/display/modals.py
token_audit/display/null_display.py
token_audit/display/plain_display.py
token_audit/display/rich_display.py
token_audit/display/session_browser.py
token_audit/display/snapshot.py
token_audit/display/theme_detect.py
token_audit/display/themes.py
token_audit/guidance/__init__.py
token_audit/guidance/exporter.py
token_audit/guidance/loader.py
token_audit/guidance/best_practices/_index.yaml
token_audit/guidance/best_practices/async_operations.md
token_audit/guidance/best_practices/caching_strategy.md
token_audit/guidance/best_practices/error_handling.md
token_audit/guidance/best_practices/large_results.md
token_audit/guidance/best_practices/progressive_disclosure.md
token_audit/guidance/best_practices/schema_versioning.md
token_audit/guidance/best_practices/security.md
token_audit/guidance/best_practices/statelessness.md
token_audit/guidance/best_practices/tool_count_limits.md
token_audit-1.0.7.dist-info/licenses/LICENSE
token_audit-1.0.7.dist-info/METADATA
token_audit-1.0.7.dist-info/WHEEL
token_audit-1.0.7.dist-info/entry_points.txt
token_audit-1.0.7.dist-info/top_level.txt
token_audit-1.0.7.dist-info/RECORD
