Metadata-Version: 2.4
Name: token-audit
Version: 1.0.7
Summary: Token usage auditor for AI coding tools. Investigate context bloat across Claude Code, Codex CLI & Gemini CLI.
Author-email: Little Bear Apps <help@littlebearapps.com>
License-Expression: MIT
Project-URL: Homepage, https://github.com/littlebearapps/token-audit
Project-URL: Documentation, https://github.com/littlebearapps/token-audit#readme
Project-URL: Repository, https://github.com/littlebearapps/token-audit
Project-URL: Source, https://github.com/littlebearapps/token-audit
Project-URL: Issues, https://github.com/littlebearapps/token-audit/issues
Project-URL: Changelog, https://github.com/littlebearapps/token-audit/blob/main/CHANGELOG.md
Project-URL: Discussions, https://github.com/littlebearapps/token-audit/discussions
Keywords: mcp,model-context-protocol,token-tracking,context-window,claude-code,codex-cli,gemini-cli,llm-cost,ai-coding,token-usage
Classifier: Development Status :: 5 - Production/Stable
Classifier: Intended Audience :: Developers
Classifier: Operating System :: OS Independent
Classifier: Programming Language :: Python :: 3
Classifier: Programming Language :: Python :: 3.8
Classifier: Programming Language :: Python :: 3.9
Classifier: Programming Language :: Python :: 3.10
Classifier: Programming Language :: Python :: 3.11
Classifier: Programming Language :: Python :: 3.12
Classifier: Programming Language :: Python :: 3.13
Classifier: Topic :: Software Development :: Libraries :: Python Modules
Classifier: Topic :: Software Development :: Quality Assurance
Classifier: Typing :: Typed
Requires-Python: >=3.8
License-File: LICENSE
Requires-Dist: rich>=13.0.0
Requires-Dist: tiktoken>=0.7.0
Requires-Dist: sentencepiece>=0.2.0
Requires-Dist: jsonschema>=4.0.0
Requires-Dist: pyyaml>=6.0.0
Requires-Dist: toml>=0.10.2
Provides-Extra: dev
Requires-Dist: pytest>=7.4.0; extra == "dev"
Requires-Dist: pytest-cov>=4.1.0; extra == "dev"
Requires-Dist: mypy>=1.7.0; extra == "dev"
Requires-Dist: types-PyYAML>=6.0.0; extra == "dev"
Requires-Dist: ruff>=0.1.0; extra == "dev"
Requires-Dist: black>=23.0.0; extra == "dev"
Requires-Dist: build>=1.0.0; extra == "dev"
Requires-Dist: twine>=4.0.0; extra == "dev"
Provides-Extra: toml
Requires-Dist: toml>=0.10.2; extra == "toml"
Provides-Extra: gemma
Requires-Dist: huggingface_hub>=0.20.0; extra == "gemma"
Provides-Extra: server
Requires-Dist: mcp>=1.0.0; extra == "server"
Requires-Dist: pydantic>=2.0.0; extra == "server"
Requires-Dist: filelock>=3.12.0; extra == "server"
Dynamic: license-file
